-- BYTECODE -- "expr-logical-2.lua":1-3
0001    ISF          1
0002    JMP      2 => 0005
0003    RET1     0   2
0004    JMP      2 => 0007
0005 => ADDVN    2   0   0  ; 1
0006    RET1     2   2
0007 => RET0     0   1

-- BYTECODE -- "expr-logical-2.lua":5-8
0001    ADDVV    2   0   1
0002    UGET     3   0      ; boo
0003    MOV      4   2
0004    ISGE     0   1
0005    JMP      5 => 0008
0006    ISTC     5   0
0007    JMP      6 => 0009
0008 => MOV      5   1
0009 => CALLT    3   3

-- BYTECODE -- "expr-logical-2.lua":0-11
0001    FNEW     0   0      ; "expr-logical-2.lua":1
0002    FNEW     1   1      ; "expr-logical-2.lua":5
0003    GGET     2   2      ; "print"
0004    MOV      3   1
0005    KSHORT   4   3
0006    KSHORT   5   7
0007    CALL     3   0   3
0008    CALLM    2   1   0
0009    UCLO     0 => 0010
0010 => RET0     0   1

