-- BYTECODE -- "goto-for-1.lua":1-10
0001    GGET     1   0      ; "ipairs"
0002    MOV      2   0
0003    CALL     1   4   2
0004    JMP      4 => 0012
0005 => MODVN    6   5   0  ; 2
0006    ISNEN    6   1      ; 0
0007    JMP      6 => 0012
0008    GGET     6   1      ; "print"
0009    KSTR     7   2      ; "list has even number"
0010    CALL     6   1   2
0011    JMP      1 => 0017
0012 => ITERC    4   3   3
0013    ITERL    4 => 0005
0014    GGET     1   1      ; "print"
0015    KSTR     2   3      ; "list lacks even number"
0016    CALL     1   1   2
0017 => RET0     0   1

-- BYTECODE -- "goto-for-1.lua":0-13
0001    FNEW     0   0      ; "goto-for-1.lua":1
0002    MOV      1   0
0003    TDUP     2   1
0004    CALL     1   1   2
0005    RET0     0   1

