-- BYTECODE -- "logical-tests-5.lua":0-8
0001    KNUM     0   0      ; 3.14
0002    GGET     1   0      ; "jit"
0003    ISF          1
0004    JMP      1 => 0012
0005    GGET     1   0      ; "jit"
0006    TGETS    1   1   1  ; "status"
0007    ISF          1
0008    JMP      2 => 0012
0009    GGET     1   2      ; "print"
0010    KSTR     2   3      ; "JIT!"
0011    CALL     1   1   2
0012 => GGET     1   2      ; "print"
0013    MOV      2   0
0014    CALL     1   1   2
0015    RET0     0   1

