-- BYTECODE -- "send-epression-call-2.lua":1-3
0001    TGETS    2   0   0  ; "value"
0002    MULVV    2   1   2
0003    RET1     2   2

-- BYTECODE -- "send-epression-call-2.lua":5-7
0001    TNEW     1 2048
0002    TSETS    0   1   0  ; "value"
0003    UGET     2   0      ; foo
0004    TSETS    2   1   1  ; "foo"
0005    RET1     1   2

-- BYTECODE -- "send-epression-call-2.lua":0-10
0001    FNEW     0   0      ; "send-epression-call-2.lua":1
0002    FNEW     1   1      ; "send-epression-call-2.lua":5
0003    GGET     2   2      ; "print"
0004    MOV      3   1
0005    KNUM     4   0      ; 3.141592
0006    CALL     3   2   2
0007    MOV      4   3
0008    TGETS    3   3   3  ; "foo"
0009    KSHORT   5   2
0010    CALL     3   0   3
0011    CALLM    2   1   0
0012    UCLO     0 => 0013
0013 => RET0     0   1

